aliyunsdkhbase/__init__.py
aliyunsdkhbase/endpoint.py
aliyunsdkhbase/request/__init__.py
aliyunsdkhbase/request/v20190101/AddUserHdfsInfoRequest.py
aliyunsdkhbase/request/v20190101/AllocatePublicNetworkAddressRequest.py
aliyunsdkhbase/request/v20190101/CheckComponentsVersionRequest.py
aliyunsdkhbase/request/v20190101/CloseBackupRequest.py
aliyunsdkhbase/request/v20190101/ConvertInstanceRequest.py
aliyunsdkhbase/request/v20190101/CreateBackupPlanRequest.py
aliyunsdkhbase/request/v20190101/CreateClusterRequest.py
aliyunsdkhbase/request/v20190101/CreateGlobalResourceRequest.py
aliyunsdkhbase/request/v20190101/CreateHBaseSlbServerRequest.py
aliyunsdkhbase/request/v20190101/CreateHbaseHaSlbRequest.py
aliyunsdkhbase/request/v20190101/CreateMultiZoneClusterRequest.py
aliyunsdkhbase/request/v20190101/CreateRestorePlanRequest.py
aliyunsdkhbase/request/v20190101/CreateServerlessClusterRequest.py
aliyunsdkhbase/request/v20190101/DeleteGlobalResourceRequest.py
aliyunsdkhbase/request/v20190101/DeleteHBaseHaDBRequest.py
aliyunsdkhbase/request/v20190101/DeleteHBaseSlbServerRequest.py
aliyunsdkhbase/request/v20190101/DeleteHbaseHaSlbRequest.py
aliyunsdkhbase/request/v20190101/DeleteInstanceRequest.py
aliyunsdkhbase/request/v20190101/DeleteMultiZoneClusterRequest.py
aliyunsdkhbase/request/v20190101/DeleteServerlessClusterRequest.py
aliyunsdkhbase/request/v20190101/DeleteUserHdfsInfoRequest.py
aliyunsdkhbase/request/v20190101/DescribeAvailableResourceRequest.py
aliyunsdkhbase/request/v20190101/DescribeBackupPlanConfigRequest.py
aliyunsdkhbase/request/v20190101/DescribeBackupPolicyRequest.py
aliyunsdkhbase/request/v20190101/DescribeBackupStatusRequest.py
aliyunsdkhbase/request/v20190101/DescribeBackupSummaryRequest.py
aliyunsdkhbase/request/v20190101/DescribeBackupTablesRequest.py
aliyunsdkhbase/request/v20190101/DescribeBackupsRequest.py
aliyunsdkhbase/request/v20190101/DescribeClusterConnectionRequest.py
aliyunsdkhbase/request/v20190101/DescribeColdStorageRequest.py
aliyun_python_sdk_hbase-2.9.9.dist-info/LICENSE
aliyun_python_sdk_hbase-2.9.9.dist-info/METADATA
aliyun_python_sdk_hbase-2.9.9.dist-info/WHEEL
aliyun_python_sdk_hbase-2.9.9.dist-info/top_level.txt
aliyun_python_sdk_hbase-2.9.9.dist-info/RECORD
